{
	"1":{
		"name":"Breakin Beats",
		"info":"著名的粤式菜肴。以贵妃鸡为原料，肉质鲜美，制作方法特别，蘸酱食用即可。",
		"res":"boluogulurou",
		"type":1,
		"unlock":1,
		"aprrule":1,
		"aprpara1":0,
		"aprpara2":0
	},
	"2":{
		"name":"Beats Top",
		"info":"什锦冬瓜帽是一道传统粤菜，以冬瓜、猪肉为主要原料，造型美观，色泽艳丽，味道清爽，营养丰富。",
		"res":"boluogulurou",
		"type":1,
		"unlock":10,
		"aprrule":1,
		"aprpara1":0,
		"aprpara2":0
	},
	"3":{
		"name":"Toprock",
		"info":"清风送爽是广东名菜，挑选精品豆腐瘦肉虾肉，配以蛋清、荸荠、葱白等，一清二楚，赏心悦目。",
		"res":"xiangjianegan",
		"type":1,
		"unlock":30,
		"aprrule":5,
		"aprpara1":2,
		"aprpara2":20
	},
	"4":{
		"name":"Beats Freeze",
		"info":"选用卤好的上等猪肉，以发菜、冬菇、青菜等激发出卤味的鲜气，造型逼真，色香味俱全。",
		"res":"xiangjianegan",
		"type":1,
		"unlock":80,
		"aprrule":1,
		"aprpara1":0,
		"aprpara2":0
	},
	"5":{
		"name":"Footwork",
		"info":"炊太极虾使用槌好的虾胶以特殊的烹调方法制成，成菜造型美观，鲜嫩清馥。",
		"res":"yidalipisa",
		"type":1,
		"unlock":300,
		"aprrule":5,
		"aprpara1":4,
		"aprpara2":10
	},
	"6":{
		"name":"Beats Power",
		"info":"著名广州菜肴以海南岛文昌鸡为主料，配以火腿、鸡肝、郊菜，经煮、蒸、炒而成。此菜造型美观，芡汁明亮。",
		"res":"shiguobanfan",
		"type":1,
		"unlock":100000,
		"aprrule":4,
		"aprpara1":0,
		"aprpara2":0
	},
	"7":{
		"name":"Popin Beats",
		"info":"干煸豆角是是一道美味的菜肴，口味咸香辣，色泽嫩绿，口感脆嫩，营养丰富。",
		"res":"yidalipisa",
		"type":2,
		"unlock":1,
		"aprrule":1,
		"aprpara1":0,
		"aprpara2":0
	},
	"8":{
		"name":"Robot Beats",
		"info":"四川凉面恰恰使用最平凡的食材，做出淳朴而又令人心醉的味道，吃完之后，数月乃至数年过去，嘴里还能念念不忘那种味道。",
		"res":"zongtongsanmingzhi",
		"type":2,
		"unlock":10,
		"aprrule":1,
		"aprpara1":0,
		"aprpara2":0
	},
	"9":{
		"name":"Popin Freeze",
		"info":"东坡肘子选用上等猪肘，套用“王弗”妙法烹调制成，色泽微黄，肥而不腻。",
		"res":"jinqiangyushousi",
		"type":2,
		"unlock":30,
		"aprrule":1,
		"aprpara1":0,
		"aprpara2":0
	},
	"10":{
		"name":"Wave Beats",
		"info":"鱼香肉丝成菜色红润、肉嫩、质鲜、富鱼香味，肉丝质地鲜嫩，菜丝香滑入口。",
		"res":"boluogulurou",
		"type":2,
		"unlock":100,
		"aprrule":5,
		"aprpara1":9,
		"aprpara2":20
	},
	"11":{
		"name":"Slide",
		"info":"常以卤制后各部牛肉切片，再红油浇之，制作精细，色泽美观，质嫩味鲜，麻辣浓香，非常适口。",
		"res":"mushaka",
		"type":2,
		"unlock":300,
		"aprrule":5,
		"aprpara1":10,
		"aprpara2":10
	},
	"12":{
		"name":"Kingtut Beats",
		"info":"麻婆豆腐外观色深红亮，红白绿相衬，豆腐形整不烂，吃起来具有麻、辣、烫、嫩、酥、香、鲜等风味，突出了川菜“麻辣”的特点。",
		"res":"shiguobanfan",
		"type":2,
		"unlock":100000,
		"aprrule":4,
		"aprpara1":0,
		"aprpara2":0
	},
	"13":{
		"name":"Lockin Beats",
		"info":"什锦冬瓜帽是一道传统粤菜，以冬瓜、猪肉为主要原料，造型美观，色泽艳丽，味道清爽，营养丰富。",
		"res":"boluogulurou",
		"type":3,
		"unlock":1,
		"aprrule":1,
		"aprpara1":0,
		"aprpara2":0
	},
	"14":{
		"name":"Move Hats",
		"info":"什锦冬瓜帽是一道传统粤菜，以冬瓜、猪肉为主要原料，造型美观，色泽艳丽，味道清爽，营养丰富。",
		"res":"mushaka",
		"type":3,
		"unlock":10,
		"aprrule":1,
		"aprpara1":0,
		"aprpara2":0
	},
	"15":{
		"name":"Point Beats",
		"info":"什锦冬瓜帽是一道传统粤菜，以冬瓜、猪肉为主要原料，造型美观，色泽艳丽，味道清爽，营养丰富。",
		"res":"shiguobanfan",
		"type":3,
		"unlock":45,
		"aprrule":1,
		"aprpara1":0,
		"aprpara2":0
	},
	"16":{
		"name":"Roll Hands",
		"info":"什锦冬瓜帽是一道传统粤菜，以冬瓜、猪肉为主要原料，造型美观，色泽艳丽，味道清爽，营养丰富。",
		"res":"boluogulurou",
		"type":3,
		"unlock":100,
		"aprrule":5,
		"aprpara1":14,
		"aprpara2":20
	},
	"17":{
		"name":"Lockin Run",
		"info":"什锦冬瓜帽是一道传统粤菜，以冬瓜、猪肉为主要原料，造型美观，色泽艳丽，味道清爽，营养丰富。",
		"res":"zhushoukaorou",
		"type":3,
		"unlock":300,
		"aprrule":1,
		"aprpara1":0,
		"aprpara2":0
	},
	"18":{
		"name":"Squat Beats",
		"info":"什锦冬瓜帽是一道传统粤菜，以冬瓜、猪肉为主要原料，造型美观，色泽艳丽，味道清爽，营养丰富。",
		"res":"yidalipisa",
		"type":3,
		"unlock":100000,
		"aprrule":4,
		"aprpara1":0,
		"aprpara2":0
	},
	"19":{
		"name":"HipHop Beats",
		"info":"什锦冬瓜帽是一道传统粤菜，以冬瓜、猪肉为主要原料，造型美观，色泽艳丽，味道清爽，营养丰富。",
		"res":"guandongzhu",
		"type":4,
		"unlock":1,
		"aprrule":1,
		"aprpara1":0,
		"aprpara2":0
	},
	"20":{
		"name":"Old School",
		"info":"什锦冬瓜帽是一道传统粤菜，以冬瓜、猪肉为主要原料，造型美观，色泽艳丽，味道清爽，营养丰富。",
		"res":"taco",
		"type":4,
		"unlock":15,
		"aprrule":1,
		"aprpara1":0,
		"aprpara2":0
	},
	"21":{
		"name":"New School",
		"info":"什锦冬瓜帽是一道传统粤菜，以冬瓜、猪肉为主要原料，造型美观，色泽艳丽，味道清爽，营养丰富。",
		"res":"boluogulurou",
		"type":4,
		"unlock":45,
		"aprrule":1,
		"aprpara1":0,
		"aprpara2":0
	},
	"22":{
		"name":"Jazz",
		"info":"什锦冬瓜帽是一道传统粤菜，以冬瓜、猪肉为主要原料，造型美观，色泽艳丽，味道清爽，营养丰富。",
		"res":"boluogulurou",
		"type":4,
		"unlock":125,
		"aprrule":1,
		"aprpara1":0,
		"aprpara2":0
	},
	"23":{
		"name":"Waackin",
		"info":"什锦冬瓜帽是一道传统粤菜，以冬瓜、猪肉为主要原料，造型美观，色泽艳丽，味道清爽，营养丰富。",
		"res":"xiangjianegan",
		"type":4,
		"unlock":300,
		"aprrule":5,
		"aprpara1":21,
		"aprpara2":15
	},
	"24":{
		"name":"Krumpin",
		"info":"什锦冬瓜帽是一道传统粤菜，以冬瓜、猪肉为主要原料，造型美观，色泽艳丽，味道清爽，营养丰富。",
		"res":"xiangjianegan",
		"type":4,
		"unlock":100000,
		"aprrule":4,
		"aprpara1":0,
		"aprpara2":0
	},
	"25":{
		"name":"Electronic Beats",
		"info":"什锦冬瓜帽是一道传统粤菜，以冬瓜、猪肉为主要原料，造型美观，色泽艳丽，味道清爽，营养丰富。",
		"res":"yidalipisa",
		"type":5,
		"unlock":1,
		"aprrule":1,
		"aprpara1":0,
		"aprpara2":0
	},
	"26":{
		"name":"Disco",
		"info":"什锦冬瓜帽是一道传统粤菜，以冬瓜、猪肉为主要原料，造型美观，色泽艳丽，味道清爽，营养丰富。",
		"res":"shiguobanfan",
		"type":5,
		"unlock":15,
		"aprrule":1,
		"aprpara1":0,
		"aprpara2":0
	},
	"27":{
		"name":"House Beats",
		"info":"什锦冬瓜帽是一道传统粤菜，以冬瓜、猪肉为主要原料，造型美观，色泽艳丽，味道清爽，营养丰富。",
		"res":"yidalipisa",
		"type":5,
		"unlock":45,
		"aprrule":1,
		"aprpara1":0,
		"aprpara2":0
	},
	"28":{
		"name":"Shuffle",
		"info":"什锦冬瓜帽是一道传统粤菜，以冬瓜、猪肉为主要原料，造型美观，色泽艳丽，味道清爽，营养丰富。",
		"res":"zongtongsanmingzhi",
		"type":5,
		"unlock":125,
		"aprrule":5,
		"aprpara1":27,
		"aprpara2":10
	},
	"29":{
		"name":"House Free",
		"info":"什锦冬瓜帽是一道传统粤菜，以冬瓜、猪肉为主要原料，造型美观，色泽艳丽，味道清爽，营养丰富。",
		"res":"jinqiangyushousi",
		"type":5,
		"unlock":300,
		"aprrule":1,
		"aprpara1":0,
		"aprpara2":0
	},
	"30":{
		"name":"Techno",
		"info":"什锦冬瓜帽是一道传统粤菜，以冬瓜、猪肉为主要原料，造型美观，色泽艳丽，味道清爽，营养丰富。",
		"res":"boluogulurou",
		"type":5,
		"unlock":100000,
		"aprrule":4,
		"aprpara1":0,
		"aprpara2":0
	},
	"31":{
		"name":"Ball Beats",
		"info":"什锦冬瓜帽是一道传统粤菜，以冬瓜、猪肉为主要原料，造型美观，色泽艳丽，味道清爽，营养丰富。",
		"res":"mushaka",
		"type":6,
		"unlock":5,
		"aprrule":1,
		"aprpara1":0,
		"aprpara2":0
	},
	"32":{
		"name":"Waltz Beats",
		"info":"什锦冬瓜帽是一道传统粤菜，以冬瓜、猪肉为主要原料，造型美观，色泽艳丽，味道清爽，营养丰富。",
		"res":"shiguobanfan",
		"type":6,
		"unlock":15,
		"aprrule":1,
		"aprpara1":0,
		"aprpara2":0
	},
	"33":{
		"name":"Tango Beats",
		"info":"什锦冬瓜帽是一道传统粤菜，以冬瓜、猪肉为主要原料，造型美观，色泽艳丽，味道清爽，营养丰富。",
		"res":"boluogulurou",
		"type":6,
		"unlock":60,
		"aprrule":1,
		"aprpara1":0,
		"aprpara2":0
	},
	"34":{
		"name":"Viennese Waltz",
		"info":"什锦冬瓜帽是一道传统粤菜，以冬瓜、猪肉为主要原料，造型美观，色泽艳丽，味道清爽，营养丰富。",
		"res":"zhushoukaorou",
		"type":6,
		"unlock":150,
		"aprrule":5,
		"aprpara1":32,
		"aprpara2":10
	},
	"35":{
		"name":"Swing Beats",
		"info":"什锦冬瓜帽是一道传统粤菜，以冬瓜、猪肉为主要原料，造型美观，色泽艳丽，味道清爽，营养丰富。",
		"res":"yidalipisa",
		"type":6,
		"unlock":300,
		"aprrule":1,
		"aprpara1":0,
		"aprpara2":0
	},
	"36":{
		"name":"Foxtrot Beats",
		"info":"什锦冬瓜帽是一道传统粤菜，以冬瓜、猪肉为主要原料，造型美观，色泽艳丽，味道清爽，营养丰富。",
		"res":"guandongzhu",
		"type":6,
		"unlock":100000,
		"aprrule":4,
		"aprpara1":0,
		"aprpara2":0
	},
	"37":{
		"name":"Latin Beats",
		"info":"什锦冬瓜帽是一道传统粤菜，以冬瓜、猪肉为主要原料，造型美观，色泽艳丽，味道清爽，营养丰富。",
		"res":"taco",
		"type":7,
		"unlock":5,
		"aprrule":1,
		"aprpara1":0,
		"aprpara2":0
	},
	"38":{
		"name":"Rumba Beats",
		"info":"什锦冬瓜帽是一道传统粤菜，以冬瓜、猪肉为主要原料，造型美观，色泽艳丽，味道清爽，营养丰富。",
		"res":"boluogulurou",
		"type":7,
		"unlock":20,
		"aprrule":1,
		"aprpara1":0,
		"aprpara2":0
	},
	"39":{
		"name":"Cha cha cha",
		"info":"什锦冬瓜帽是一道传统粤菜，以冬瓜、猪肉为主要原料，造型美观，色泽艳丽，味道清爽，营养丰富。",
		"res":"boluogulurou",
		"type":7,
		"unlock":60,
		"aprrule":5,
		"aprpara1":38,
		"aprpara2":10
	},
	"40":{
		"name":"Jive Beats",
		"info":"什锦冬瓜帽是一道传统粤菜，以冬瓜、猪肉为主要原料，造型美观，色泽艳丽，味道清爽，营养丰富。",
		"res":"xiangjianegan",
		"type":7,
		"unlock":150,
		"aprrule":1,
		"aprpara1":0,
		"aprpara2":0
	},
	"41":{
		"name":"Samba Beats",
		"info":"什锦冬瓜帽是一道传统粤菜，以冬瓜、猪肉为主要原料，造型美观，色泽艳丽，味道清爽，营养丰富。",
		"res":"xiangjianegan",
		"type":7,
		"unlock":300,
		"aprrule":1,
		"aprpara1":0,
		"aprpara2":0
	},
	"42":{
		"name":"Matador Beats",
		"info":"什锦冬瓜帽是一道传统粤菜，以冬瓜、猪肉为主要原料，造型美观，色泽艳丽，味道清爽，营养丰富。",
		"res":"yidalipisa",
		"type":7,
		"unlock":100000,
		"aprrule":4,
		"aprpara1":0,
		"aprpara2":0
	},
	"43":{
		"name":"Modern Beats",
		"info":"什锦冬瓜帽是一道传统粤菜，以冬瓜、猪肉为主要原料，造型美观，色泽艳丽，味道清爽，营养丰富。",
		"res":"shiguobanfan",
		"type":8,
		"unlock":5,
		"aprrule":1,
		"aprpara1":0,
		"aprpara2":0
	},
	"44":{
		"name":"Graham Style",
		"info":"什锦冬瓜帽是一道传统粤菜，以冬瓜、猪肉为主要原料，造型美观，色泽艳丽，味道清爽，营养丰富。",
		"res":"yidalipisa",
		"type":8,
		"unlock":20,
		"aprrule":1,
		"aprpara1":0,
		"aprpara2":0
	},
	"45":{
		"name":"Humphrey Style",
		"info":"什锦冬瓜帽是一道传统粤菜，以冬瓜、猪肉为主要原料，造型美观，色泽艳丽，味道清爽，营养丰富。",
		"res":"zongtongsanmingzhi",
		"type":8,
		"unlock":60,
		"aprrule":1,
		"aprpara1":0,
		"aprpara2":0
	},
	"46":{
		"name":"Limon Beats",
		"info":"什锦冬瓜帽是一道传统粤菜，以冬瓜、猪肉为主要原料，造型美观，色泽艳丽，味道清爽，营养丰富。",
		"res":"jinqiangyushousi",
		"type":8,
		"unlock":200,
		"aprrule":1,
		"aprpara1":0,
		"aprpara2":0
	},
	"47":{
		"name":"Horton Style",
		"info":"什锦冬瓜帽是一道传统粤菜，以冬瓜、猪肉为主要原料，造型美观，色泽艳丽，味道清爽，营养丰富。",
		"res":"boluogulurou",
		"type":8,
		"unlock":300,
		"aprrule":1,
		"aprpara1":0,
		"aprpara2":0
	},
	"48":{
		"name":"Postmodern",
		"info":"什锦冬瓜帽是一道传统粤菜，以冬瓜、猪肉为主要原料，造型美观，色泽艳丽，味道清爽，营养丰富。",
		"res":"xiangjianegan",
		"type":8,
		"unlock":100000,
		"aprrule":4,
		"aprpara1":0,
		"aprpara2":0
	},
	"49":{
		"name":"Nations Beats",
		"info":"什锦冬瓜帽是一道传统粤菜，以冬瓜、猪肉为主要原料，造型美观，色泽艳丽，味道清爽，营养丰富。",
		"res":"xiangjianegan",
		"type":9,
		"unlock":5,
		"aprrule":1,
		"aprpara1":0,
		"aprpara2":0
	},
	"50":{
		"name":"Cancan Beats",
		"info":"什锦冬瓜帽是一道传统粤菜，以冬瓜、猪肉为主要原料，造型美观，色泽艳丽，味道清爽，营养丰富。",
		"res":"yidalipisa",
		"type":9,
		"unlock":20,
		"aprrule":1,
		"aprpara1":0,
		"aprpara2":0
	},
	"51":{
		"name":"Hula Beats",
		"info":"什锦冬瓜帽是一道传统粤菜，以冬瓜、猪肉为主要原料，造型美观，色泽艳丽，味道清爽，营养丰富。",
		"res":"shiguobanfan",
		"type":9,
		"unlock":80,
		"aprrule":1,
		"aprpara1":0,
		"aprpara2":0
	},
	"52":{
		"name":"Belly Beats",
		"info":"什锦冬瓜帽是一道传统粤菜，以冬瓜、猪肉为主要原料，造型美观，色泽艳丽，味道清爽，营养丰富。",
		"res":"yidalipisa",
		"type":9,
		"unlock":200,
		"aprrule":1,
		"aprpara1":0,
		"aprpara2":0
	},
	"53":{
		"name":"Pole Beats",
		"info":"什锦冬瓜帽是一道传统粤菜，以冬瓜、猪肉为主要原料，造型美观，色泽艳丽，味道清爽，营养丰富。",
		"res":"zongtongsanmingzhi",
		"type":9,
		"unlock":300,
		"aprrule":1,
		"aprpara1":0,
		"aprpara2":0
	},
	"54":{
		"name":"Pavan Beats",
		"info":"什锦冬瓜帽是一道传统粤菜，以冬瓜、猪肉为主要原料，造型美观，色泽艳丽，味道清爽，营养丰富。",
		"res":"jinqiangyushousi",
		"type":9,
		"unlock":100000,
		"aprrule":4,
		"aprpara1":0,
		"aprpara2":0
	},
	"55":{
		"name":"Free Beats",
		"info":"什锦冬瓜帽是一道传统粤菜，以冬瓜、猪肉为主要原料，造型美观，色泽艳丽，味道清爽，营养丰富。",
		"res":"boluogulurou",
		"type":10,
		"unlock":5,
		"aprrule":1,
		"aprpara1":0,
		"aprpara2":0
	},
	"56":{
		"name":"Silly Move",
		"info":"什锦冬瓜帽是一道传统粤菜，以冬瓜、猪肉为主要原料，造型美观，色泽艳丽，味道清爽，营养丰富。",
		"res":"mushaka",
		"type":10,
		"unlock":25,
		"aprrule":1,
		"aprpara1":0,
		"aprpara2":0
	},
	"57":{
		"name":"Free Heart",
		"info":"什锦冬瓜帽是一道传统粤菜，以冬瓜、猪肉为主要原料，造型美观，色泽艳丽，味道清爽，营养丰富。",
		"res":"shiguobanfan",
		"type":10,
		"unlock":80,
		"aprrule":1,
		"aprpara1":0,
		"aprpara2":0
	},
	"58":{
		"name":"Roll Body",
		"info":"什锦冬瓜帽是一道传统粤菜，以冬瓜、猪肉为主要原料，造型美观，色泽艳丽，味道清爽，营养丰富。",
		"res":"boluogulurou",
		"type":10,
		"unlock":200,
		"aprrule":5,
		"aprpara1":56,
		"aprpara2":10
	},
	"59":{
		"name":"Up Down",
		"info":"什锦冬瓜帽是一道传统粤菜，以冬瓜、猪肉为主要原料，造型美观，色泽艳丽，味道清爽，营养